{
  "required": true,
  "package": "io.github.anvilloystudio.minimods.api.mixins",
  "priority": 2147483647,
  "minVersion": "0.8.5",
  "mixins": [
    "ColorMixin",
    "DoorTileMixin",
    "GameMixin",
    "InputHandlerMixin",
    "ItemsMixin",
    "LevelGenAccessorMixin",
    "LevelGenMixin",
    "MaterialMixin",
    "MenuMixin",
    "OreTileMixin",
    "OreTypeMixin",
    "PlayerMixin",
    "RendererMixin",
    "ScreenMixin",
    "SpriteMixin",
    "SpritePxMixin",
    "TileMixin",
    "TilesMixin",
    "TitleDisplayMixin",
    "ToolTypeMixin",
    "UpdaterMixin"
  ],
  "injectors": {
    "defaultRequire": 1
  }
}
